pytorch_warmup_scheduler/__init__.py
pytorch_warmup_scheduler/warmup_scheduler.py
pytorch_warmup_scheduler-0.0.1.dist-info/LICENSE
pytorch_warmup_scheduler-0.0.1.dist-info/METADATA
pytorch_warmup_scheduler-0.0.1.dist-info/WHEEL
pytorch_warmup_scheduler-0.0.1.dist-info/top_level.txt
pytorch_warmup_scheduler-0.0.1.dist-info/RECORD
