Metadata-Version: 2.1
Name: pytorch-warmup-scheduler
Version: 0.0.1
Summary: PyTorch implementation of warmup scheduler
Home-page: https://github.com/hysts/pytorch_warmup-scheduler
Author: hysts
License: MIT
Platform: Linux
Platform: Mac OS-X
Requires-Python: >=3.7
License-File: LICENSE
Requires-Dist: torch (>=1.4)
